MANIFEST.in
README.md
kickstart.py
setup.py
kickstart.egg-info/PKG-INFO
kickstart.egg-info/SOURCES.txt
kickstart.egg-info/dependency_links.txt
kickstart.egg-info/requires.txt
kickstart.egg-info/top_level.txt
kickstarter/__init__.py
kickstarter/templates/default/README.md
kickstarter/templates/default/config.yaml
kickstarter/templates/default/fabfile.py
kickstarter/templates/default/requirements.pip
kickstarter/templates/default/run.py
kickstarter/templates/default/setup.py
kickstarter/templates/default/default/__init__.py
kickstarter/templates/default/default/models.py
kickstarter/templates/default/default/tests.py
kickstarter/templates/default/default/views.py
kickstarter/templates/default/default/conf/__init__.py
kickstarter/templates/default/default/conf/live.py
kickstarter/templates/default/default/conf/local.py
kickstarter/templates/default/default/conf/stage.py
kickstarter/templates/default/default/conf/test.py
kickstarter/templates/default/default/templates/404.html
kickstarter/templates/default/default/templates/500.html
kickstarter/templates/default/default/templates/base.html
kickstarter/templates/default/server/live/nginx.conf
kickstarter/templates/default/server/local/nginx.conf
kickstarter/templates/default/server/stage/nginx.conf
kickstarter/templates/default/server/test/nginx.conf
kickstarter/templates/default/static/css/styles.css
kickstarter/templates/flask/README.md
kickstarter/templates/flask/config.yaml
kickstarter/templates/flask/fabfile.py
kickstarter/templates/flask/requirements.pip
kickstarter/templates/flask/run.py
kickstarter/templates/flask/setup.py
kickstarter/templates/flask/flask/__init__.py
kickstarter/templates/flask/flask/models.py
kickstarter/templates/flask/flask/tests.py
kickstarter/templates/flask/flask/views.py
kickstarter/templates/flask/flask/conf/__init__.py
kickstarter/templates/flask/flask/conf/live.py
kickstarter/templates/flask/flask/conf/local.py
kickstarter/templates/flask/flask/conf/stage.py
kickstarter/templates/flask/flask/conf/test.py
kickstarter/templates/flask/flask/templates/404.html
kickstarter/templates/flask/flask/templates/500.html
