Metadata-Version: 1.0
Name: kickstart
Version: 0.296
Summary: Framework agnostic setup script
Home-page: https://github.com/rlayte/kickstart
Author: Richard Layte
Author-email: rich.layte@gmail.com
License: UNKNOWN
Platform: UNKNOWN
